[
    {
        "1c124154ccb8c775fbbc4e8a7d9f5cca":[
            {
                "LexRank":[
                    {
                        "rouge-1":{
                            "r":0.27218934911242604,
                            "p":0.4339622641509434,
                            "f":0.3345454498078678
                        },
                        "rouge-2":{
                            "r":0.05019305019305019,
                            "p":0.0896551724137931,
                            "f":0.06435643104168742
                        },
                        "rouge-l":{
                            "r":0.20118343195266272,
                            "p":0.32075471698113206,
                            "f":0.24727272253514054
                        }
                    }
                ]
            },
            {
                "TextRank":[
                    {
                        "rouge-1":{
                            "r":0.20118343195266272,
                            "p":0.2905982905982906,
                            "f":0.23776223292752713
                        },
                        "rouge-2":{
                            "r":0.03474903474903475,
                            "p":0.049723756906077346,
                            "f":0.04090908606621958
                        },
                        "rouge-l":{
                            "r":0.17159763313609466,
                            "p":0.24786324786324787,
                            "f":0.20279719796249218
                        }
                    }
                ]
            },
            {
                "Luhn":[
                    {
                        "rouge-1":{
                            "r":0.2958579881656805,
                            "p":0.32051282051282054,
                            "f":0.3076923027003078
                        },
                        "rouge-2":{
                            "r":0.06563706563706563,
                            "p":0.07327586206896551,
                            "f":0.06924643086033361
                        },
                        "rouge-l":{
                            "r":0.24260355029585798,
                            "p":0.26282051282051283,
                            "f":0.25230768731569236
                        }
                    }
                ]
            },
            {
                "Lsa":[
                    {
                        "rouge-1":{
                            "r":0.1952662721893491,
                            "p":0.4074074074074074,
                            "f":0.2639999956195201
                        },
                        "rouge-2":{
                            "r":0.03474903474903475,
                            "p":0.09,
                            "f":0.05013927174680551
                        },
                        "rouge-l":{
                            "r":0.15976331360946747,
                            "p":0.3333333333333333,
                            "f":0.2159999956195201
                        }
                    }
                ]
            }
        ]
    },
    {
        "2c02d6960625b1d510098f7857f90ab9":[
            {
                "LexRank":[
                    {
                        "rouge-1":{
                            "r":0.15,
                            "p":0.39344262295081966,
                            "f":0.21719456613910446
                        },
                        "rouge-2":{
                            "r":0.05084745762711865,
                            "p":0.16901408450704225,
                            "f":0.0781758922097849
                        },
                        "rouge-l":{
                            "r":0.125,
                            "p":0.32786885245901637,
                            "f":0.1809954711164801
                        }
                    }
                ]
            },
            {
                "TextRank":[
                    {
                        "rouge-1":{
                            "r":0.19375,
                            "p":0.29245283018867924,
                            "f":0.23308270197297765
                        },
                        "rouge-2":{
                            "r":0.05084745762711865,
                            "p":0.07792207792207792,
                            "f":0.061538456759500704
                        },
                        "rouge-l":{
                            "r":0.15,
                            "p":0.22641509433962265,
                            "f":0.18045112302560928
                        }
                    }
                ]
            },
            {
                "Luhn":[
                    {
                        "rouge-1":{
                            "r":0.175,
                            "p":0.2916666666666667,
                            "f":0.21874999531250008
                        },
                        "rouge-2":{
                            "r":0.05508474576271186,
                            "p":0.0962962962962963,
                            "f":0.07008085790425848
                        },
                        "rouge-l":{
                            "r":0.15625,
                            "p":0.2604166666666667,
                            "f":0.19531249531250014
                        }
                    }
                ]
            },
            {
                "Lsa":[
                    {
                        "rouge-1":{
                            "r":0.0875,
                            "p":0.18666666666666668,
                            "f":0.11914893182435506
                        },
                        "rouge-2":{
                            "r":0.00847457627118644,
                            "p":0.025,
                            "f":0.012658224066657115
                        },
                        "rouge-l":{
                            "r":0.08125,
                            "p":0.17333333333333334,
                            "f":0.11063829352648276
                        }
                    }
                ]
            }
        ]
    }
]